lambda_deploy/__init__.py
lambda_deploy/__main__.py
lambda_deploy/cli/__init__.py
lambda_deploy/cli/cli.py
lambda_deploy/cli/commands/__init__.py
lambda_deploy/cli/commands/bootstrap.py
lambda_deploy/cli/commands/deploy.py
lambda_deploy/cli/commands/info.py
lambda_deploy/core/__init__.py
lambda_deploy/core/deployer.py
lambda_deploy/utils/__init__.py
lambda_deploy/utils/config_processor.py
lambda_deploy/utils/logging.py
tests/__init__.py
tests/test_config_processor.py
tests/test_deployer.py
lambda_deploy_cli-0.1.3.dist-info/METADATA
lambda_deploy_cli-0.1.3.dist-info/WHEEL
lambda_deploy_cli-0.1.3.dist-info/entry_points.txt
lambda_deploy_cli-0.1.3.dist-info/top_level.txt
lambda_deploy_cli-0.1.3.dist-info/RECORD
