Metadata-Version: 2.1
Name: lambda-deploy-cli
Version: 0.1.3
Summary: A cli for deploying AWS Lambda functions
Author: Povio
Author-email: goran.parapid@povio.com
Classifier: Programming Language :: Python :: 3.8
Classifier: Programming Language :: Python :: 3.9
Classifier: Programming Language :: Python :: 3.10
Classifier: Programming Language :: Python :: 3.11
Classifier: Programming Language :: Python :: 3.12
Requires-Python: >=3.8
Requires-Dist: boto3>=1.26.0
Requires-Dist: pyyaml>=6.0
Requires-Dist: click>=8.1.0
Requires-Dist: pytest>=7.0.0
Requires-Dist: pytest-cov>=4.0.0
Requires-Dist: black>=23.0.0
Requires-Dist: isort>=5.12.0
Requires-Dist: flake8>=6.0.0
Requires-Dist: mypy>=1.0.0
Requires-Dist: types-PyYAML>=6.0.0
Requires-Dist: types-boto3>=1.0.0
